[
    {
        "ambient_events": [],
        "description": {
            "default": ""
        },
        "exits": {
            "northeast": "room_1766107071981_571",
            "northwest": "room_1766107074505_244",
            "south": "town_square"
        },
        "flags": {
            "is_node": true,
            "is_super_node": false,
            "is_sanctuary": true,
            "is_pvp": false,
            "magic_allowed": true,
            "stealing_allowed": true,
            "teleport_in_allowed": true,
            "teleport_out_allowed": true,
            "hiding_allowed": true,
            "sneak_in_allowed": true,
            "sneak_out_allowed": true
        },
        "hidden_objects": [],
        "illumination": 50,
        "interior_id": "rooms_golden_market",
        "is_outdoor": true,
        "is_table": false,
        "name": "Town Well - South",
        "objects": [
            {
                "name": "Town Well",
                "description": "",
                "keywords": [
                    "town well",
                    "well"
                ],
                "verbs": [
                    "look",
                    "Climb"
                ],
                "interactions": {
                    "Climb": {
                        "type": "move",
                        "value": "well_bottom"
                    }
                }
            }
        ],
        "room_id": "room_1766106929120_953",
        "x": -5,
        "y": -1,
        "z": 0
    },
    {
        "ambient_events": [],
        "description": {
            "default": ""
        },
        "exits": {
            "northwest": "room_1766107073364_416",
            "southwest": "room_1766106929120_953"
        },
        "flags": {
            "is_node": true,
            "is_super_node": false,
            "is_sanctuary": true,
            "is_pvp": false,
            "magic_allowed": true,
            "stealing_allowed": true,
            "teleport_in_allowed": true,
            "teleport_out_allowed": true,
            "hiding_allowed": true,
            "sneak_in_allowed": true,
            "sneak_out_allowed": true
        },
        "hidden_objects": [],
        "illumination": 50,
        "interior_id": "town_center_well",
        "is_outdoor": true,
        "is_table": false,
        "name": "Town Well - East",
        "objects": [
            {
                "name": "Town Well",
                "description": "",
                "keywords": [
                    "town well",
                    "well"
                ],
                "verbs": [
                    "look",
                    "Climb"
                ],
                "interactions": {
                    "Climb": {
                        "type": "move",
                        "value": "well_bottom"
                    }
                }
            }
        ],
        "room_id": "room_1766107071981_571",
        "x": -4,
        "y": 0,
        "z": 0
    },
    {
        "ambient_events": [],
        "description": {
            "default": "You stand under the northern eaves of the town's massive central well. The conical roof creates a deep, permanent shadow here, and the rough-hewn grey stones of the base are coated in a thick, velvety moss. One of the four heavy timber posts supporting the roof rises here, its wood darkened by soot and damp. A sturdy, iron-bound oak bench sits between the timber post and the mossy stone base."
        },
        "exits": {
            "southeast": "room_1766107071981_571",
            "southwest": "room_1766107074505_244"
        },
        "flags": {
            "is_node": true,
            "is_super_node": false,
            "is_sanctuary": true,
            "is_pvp": false,
            "magic_allowed": true,
            "stealing_allowed": true,
            "teleport_in_allowed": true,
            "teleport_out_allowed": true,
            "hiding_allowed": true,
            "sneak_in_allowed": true,
            "sneak_out_allowed": true
        },
        "hidden_objects": [
            {
                "name": "a rope",
                "description": "",
                "keywords": [
                    "rope"
                ],
                "verbs": [
                    "look",
                    "climb",
                    "look at"
                ],
                "interactions": {
                    "climb": {
                        "type": "move",
                        "value": "well_bottom"
                    },
                    "look at": {
                        "type": "text",
                        "value": "A thick, braided hemp rope hangs from the central windlass beam, disappearing into the pitch-black depth of the well. It looks thick and incredibly sturdy\u2014easily strong enough to hold the weight of a fully armored adventurer if one were to climb down."
                    }
                },
                "perception_dc": 1
            }
        ],
        "illumination": 50,
        "interior_id": "town_center_well",
        "is_outdoor": true,
        "is_table": false,
        "name": "Town Well - North",
        "objects": [
            {
                "name": "Town Well",
                "description": "",
                "keywords": [
                    "town well",
                    "well"
                ],
                "verbs": [
                    "look",
                    "look at"
                ],
                "interactions": {
                    "look at": {
                        "type": "text",
                        "value": "The well is a fortress of water storage. On this side, the grey stones are slick with green moss and stained black by coal dust. The heavy timber beams hold up the shingled roof, protecting the shaft from the city's grime. It looks ancient and immovable."
                    }
                }
            }
        ],
        "room_id": "room_1766107073364_416",
        "x": -5,
        "y": 1,
        "z": 0
    },
    {
        "ambient_events": [],
        "description": {
            "default": ""
        },
        "exits": {
            "northeast": "room_1766107073364_416",
            "southeast": "room_1766106929120_953"
        },
        "flags": {
            "is_node": true,
            "is_super_node": false,
            "is_sanctuary": true,
            "is_pvp": false,
            "magic_allowed": true,
            "stealing_allowed": true,
            "teleport_in_allowed": true,
            "teleport_out_allowed": true,
            "hiding_allowed": true,
            "sneak_in_allowed": true,
            "sneak_out_allowed": true
        },
        "hidden_objects": [],
        "illumination": 50,
        "interior_id": "town_center_well",
        "is_outdoor": true,
        "is_table": false,
        "name": "Town Well - West",
        "objects": [
            {
                "name": "Town Well",
                "description": "",
                "keywords": [
                    "town well",
                    "well"
                ],
                "verbs": [
                    "look",
                    "Climb"
                ],
                "interactions": {
                    "Climb": {
                        "type": "move",
                        "value": "well_bottom"
                    }
                }
            },
            {
                "name": "a bench",
                "description": "A nice stone bench.",
                "keywords": [
                    "bench"
                ],
                "verbs": [
                    "look",
                    "look on",
                    "look at",
                    "look under",
                    "look behind"
                ],
                "interactions": {
                    "look on": {
                        "type": "text",
                        "value": "The top of the bench is smooth stone, it looks like a nice place to sit."
                    },
                    "look at": {
                        "type": "text",
                        "value": "A nice stone bench."
                    },
                    "look under": {
                        "type": "text",
                        "value": "The grass is growing up the legs of the bench, the gardners seem to have missed this bench when tending to the area."
                    },
                    "look behind": {
                        "type": "text",
                        "value": "There is a bit of room to fit something behind the bench and between the well."
                    }
                }
            },
            {
                "item_id": "iron_dagger",
                "is_item": true
            }
        ],
        "room_id": "room_1766107074505_244",
        "x": -6,
        "y": 0,
        "z": 0
    }
]